{
  "collectionName": "components_elements_links",
  "info": {
    "displayName": "Odkaz",
    "icon": "attachment"
  },
  "options": {},
  "attributes": {
    "page": {
      "type": "relation",
      "relation": "oneToOne",
      "target": "api::page.page"
    },
    "anchor": {
      "type": "string"
    },
    "url": {
      "type": "string"
    },
    "file": {
      "type": "media",
      "multiple": false,
      "allowedTypes": [
        "images",
        "files",
        "videos",
        "audios"
      ]
    }
  },
  "config": {}
}
