{
  "collectionName": "components_components_expandable_sections",
  "info": {
    "displayName": "expandable-section",
    "icon": "expand"
  },
  "options": {},
  "attributes": {
    "title": {
      "type": "string",
      "required": true
    },
    "description": {
      "type": "text",
      "required": false
    },
    "contact_name": {
      "type": "string",
      "required": false
    },
    "contact_email": {
      "type": "email",
      "required": false
    },
    "contact_phone": {
      "type": "string",
      "required": false
    },
    "files": {
      "type": "component",
      "repeatable": true,
      "component": "elements.file-attachment",
      "required": false
    },
    "default_open": {
      "type": "boolean",
      "default": false,
      "required": false
    }
  },
  "config": {}
}
