{
  "collectionName": "components_components_sliders",
  "info": {
    "displayName": "Slider",
    "icon": "layer"
  },
  "options": {},
  "attributes": {
    "slides": {
      "type": "component",
      "component": "elements.slide",
      "repeatable": true,
      "required": true
    },
    "autoplay": {
      "type": "boolean",
      "required": false,
      "default": false
    },
    "autoplay_interval": {
      "type": "integer",
      "required": false,
      "default": 5000
    }
  },
  "config": {}
}
